maxminddb_rust-0.3.0.dist-info/METADATA
maxminddb_rust-0.3.0.dist-info/WHEEL
maxminddb_rust-0.3.0.dist-info/licenses/LICENSE
maxminddb_rust.pyi
maxminddb_rust/__init__.py
maxminddb_rust/__init__.pyi
maxminddb_rust/maxminddb_rust.cpython-314-x86_64-linux-gnu.so
maxminddb_rust/py.typed
py.typed
maxminddb_rust-0.3.0.dist-info/RECORD
