Metadata-Version: 2.4
Name: maxminddb-rust
Version: 0.3.0
Classifier: Development Status :: 4 - Beta
Classifier: Intended Audience :: Developers
Classifier: License :: OSI Approved :: ISC License (ISCL)
Classifier: Programming Language :: Python :: 3
Classifier: Programming Language :: Python :: 3.8
Classifier: Programming Language :: Python :: 3.9
Classifier: Programming Language :: Python :: 3.10
Classifier: Programming Language :: Python :: 3.11
Classifier: Programming Language :: Python :: 3.12
Classifier: Programming Language :: Python :: 3.13
Classifier: Programming Language :: Python :: 3.14
Classifier: Programming Language :: Rust
Classifier: Programming Language :: Python :: Implementation :: CPython
Classifier: Topic :: Software Development :: Libraries :: Python Modules
Classifier: Topic :: Database
Classifier: Topic :: Internet
Requires-Dist: pytest>=8.3.5 ; extra == 'test'
Provides-Extra: test
License-File: LICENSE
Summary: Rust-based Python binding for MaxMind DB - high-performance alternative to maxminddb
Keywords: maxmind,geoip,geolocation,ip-address,mmdb
Author-email: Gregory Oschwald <oschwald@gmail.com>
License: ISC
Requires-Python: >=3.8
Project-URL: Homepage, https://github.com/oschwald/maxminddb-rust-python
Project-URL: Repository, https://github.com/oschwald/maxminddb-rust-python
Project-URL: Bug Tracker, https://github.com/oschwald/maxminddb-rust-python/issues
Project-URL: Changelog, https://github.com/oschwald/maxminddb-rust-python/blob/main/CHANGELOG.md
Project-URL: Migration Guide, https://github.com/oschwald/maxminddb-rust-python/blob/main/MIGRATION.md
Project-URL: Contributing, https://github.com/oschwald/maxminddb-rust-python/blob/main/CONTRIBUTING.md
